setup.py
californiasos/__init__.py
californiasos/search.py
californiasos/search_test.py
californiasos.egg-info/PKG-INFO
californiasos.egg-info/SOURCES.txt
californiasos.egg-info/dependency_links.txt
californiasos.egg-info/requires.txt
californiasos.egg-info/top_level.txt