Metadata-Version: 1.1
Name: californiasos
Version: 0.1.1
Summary: Python bindings to the California SOS Business Entity Search
Home-page: https://github.com/jacobgreenleaf/californiasos
Author: Jacob Greenleaf
Author-email: jacob@jacobgreenleaf.com
License: MIT
Platform: UNKNOWN
Classifier: Development Status :: 3 - Alpha
Classifier: Intended Audience :: Developers
Classifier: Programming Language :: Python :: 3
Classifier: Topic :: Internet :: WWW/HTTP
Classifier: License :: OSI Approved :: MIT License
